kim2014convolutional/__init__.py
kim2014convolutional/model.py
kim2014convolutional-0.2.0.dist-info/DESCRIPTION.rst
kim2014convolutional-0.2.0.dist-info/METADATA
kim2014convolutional-0.2.0.dist-info/RECORD
kim2014convolutional-0.2.0.dist-info/WHEEL
kim2014convolutional-0.2.0.dist-info/metadata.json
kim2014convolutional-0.2.0.dist-info/top_level.txt
kim2014convolutional-0.2.0.dist-info/zip-safe
