Metadata-Version: 2.0
Name: kim2014convolutional
Version: 0.2.0
Summary: Implementation of kim2014convolutional
Home-page: https://github.com/wnohang/kim2014convolutional
Author: Cesar Perez
Author-email: cperez@wnohang.com
License: MIT
Keywords: research model
Platform: UNKNOWN
Classifier: Development Status :: 3 - Alpha
Classifier: Intended Audience :: Developers
Classifier: Intended Audience :: Science/Research
Classifier: License :: OSI Approved :: MIT License
Classifier: Programming Language :: Python :: 3.6
Classifier: Topic :: Education
Classifier: Topic :: Scientific/Engineering :: Artificial Intelligence
Requires-Dist: keras
